{
  "name": "Skeleton",
  "meta": {
    "size": "Medium",
    "type": "undead",
    "alignment": "Lawful Evil"
  },
  "attributes": {
    "strength": {"score": 10, "modifier": 0},
    "dexterity": {"score": 14, "modifier": 2},
    "constitution": {"score": 15, "modifier": 2},
    "intelligence": {"score": 6, "modifier": -2},
    "wisdom": {"score": 8, "modifier": -1},
    "charisma": {"score": 5, "modifier": -3}
  },
  "stats": {
    "armor_class": {"value": 13, "type": "Armor Scraps"},
    "hit_points": {"average": 13, "formula": "2d8 + 4"},
    "speed": {
      "walk": {"value": 30, "unit": "ft"}
    },
    "damage_vulnerabilities": ["bludgeoning"],
    "damage_immunities": ["poison"],
    "condition_immunities": ["exhaustion", "poisoned"],
    "senses": {"darkvision": 60, "passive_perception": 9},
    "languages": ["understands all languages it knew in life but can't speak"],
    "challenge": {"rating": "1/4", "xp": 50},
    "proficiency_bonus": 2
  },
  "actions": [
    {
      "name": "Shortsword",
      "description": "Melee Weapon Attack: +4 to hit, reach 5 ft., one target. Hit: 5 (1d6 + 2) piercing damage.",
      "type": "Melee Weapon Attack",
      "attack_bonus": 4,
      "reach": {"value": 5, "unit": "ft"},
      "target": "one target",
      "damage": {"average": 5, "formula": "1d6 + 2", "type": "piercing"}
    },
    {
      "name": "Shortbow",
      "description": "Ranged Weapon Attack: +4 to hit, range 80/320 ft., one target. Hit: 5 (1d6 + 2) piercing damage.",
      "type": "Ranged Weapon Attack",
      "attack_bonus": 4,
      "range": {"normal": 80, "long": 320, "unit": "ft"},
      "target": "one target",
      "damage": {"average": 5, "formula": "1d6 + 2", "type": "piercing"}
    }
  ]
}
